eoscale/__init__.py
eoscale/data_types.py
eoscale/eo_executors.py
eoscale/manager.py
eoscale/shared.py
eoscale/utils.py
eoscale/core/__init__.py
eoscale/filters/__init__.py
eoscale/filters/concatenate_images.py
eoscale/filters/generic_kernel.py
eoscale/filters/stats_minmax.py
eoscale-1.0.0.dist-info/AUTHORS.md
eoscale-1.0.0.dist-info/LICENSE
eoscale-1.0.0.dist-info/METADATA
eoscale-1.0.0.dist-info/WHEEL
eoscale-1.0.0.dist-info/top_level.txt
eoscale-1.0.0.dist-info/RECORD
