Metadata-Version: 2.1
Name: eoscale
Version: 1.0.0
Summary: Generic Earth Observation multiprocessing Python framework
Author: Pierre Lassalle
Author-email: pierre.lassalle@cnes.fr
License: Apache V2.0
Requires-Python: >=3.8
License-File: LICENSE
License-File: AUTHORS.md
Requires-Dist: numpy
Requires-Dist: pyyaml
Requires-Dist: rasterio
Requires-Dist: laspy
Requires-Dist: tqdm
Requires-Dist: scipy
Requires-Dist: pytest
Requires-Dist: sphinx
Requires-Dist: sphinx-autodoc-typehints
Requires-Dist: sphinx-rtd-theme
Requires-Dist: myst-nb==0.17.2
